cvdataloading/__init__.py
cvdataloading/_utils.py
cvdataloading/cvdata.py
cvdataloading/data_items.py
cvdataloading/processing.py
cvdataloading/transforms.py
cvdataloading-0.1.0a2.dist-info/LICENSE
cvdataloading-0.1.0a2.dist-info/METADATA
cvdataloading-0.1.0a2.dist-info/WHEEL
cvdataloading-0.1.0a2.dist-info/top_level.txt
cvdataloading-0.1.0a2.dist-info/RECORD
