Metadata-Version: 2.1
Name: cvdataloading
Version: 0.1.0a2
Summary: A PyTorch-based dynamic dataloading library
Home-page: https://github.com/atong28/CVData
Author: Anthony Tong
Author-email: atong28.usa@gmail.com
License: Apache License 2.0
License-File: LICENSE
Requires-Dist: opencv-python <=4.9.0.80,>=4.6.0
Requires-Dist: Pillow <=10.3.0,>=8.0.0
Requires-Dist: PyYAML <=6.0.1,>=5.4.0
Requires-Dist: tqdm <=4.66.2,>=4.1.0
Requires-Dist: numpy <2.0.0,>=1.18.0
Requires-Dist: pandas <=2.2.2,>=1.0.0
Requires-Dist: torch <=2.3.0,>=2.0.0
Requires-Dist: torchvision <=0.18.0,>=0.15.1
Requires-Dist: typing-extensions <=4.11.0,>=4.0.0
Requires-Dist: xmltodict <=0.13.0,>=0.12.0
Requires-Dist: jsonpickle <=3.1.0,>=3.0.0
Requires-Dist: matplotlib <=3.8.4,>=3.6.0
